vktrs/__init__.py
vktrs/api.py
vktrs/asr.py
vktrs/hf.py
vktrs/tsp.py
vktrs/utils.py
vktrs/youtube.py
vktrs-0.1.8.dist-info/LICENSE
vktrs-0.1.8.dist-info/METADATA
vktrs-0.1.8.dist-info/WHEEL
vktrs-0.1.8.dist-info/top_level.txt
vktrs-0.1.8.dist-info/RECORD
