Metadata-Version: 2.1
Name: vktrs
Version: 0.1.8
Summary: Video Killed The Radio Star
License: MIT
Requires-Python: >=3.7
License-File: LICENSE
Requires-Dist: yt-dlp
Requires-Dist: python-tsp
Requires-Dist: webvtt-py
Requires-Dist: pytokenizations
Requires-Dist: pandas
Requires-Dist: beautifulsoup4
Requires-Dist: omegaconf
Requires-Dist: scipy
Requires-Dist: toolz
Requires-Dist: numpy
Requires-Dist: lxml
Provides-Extra: api
Requires-Dist: stability-sdk (>=0.2.1) ; extra == 'api'
Provides-Extra: hf
Requires-Dist: diffusers ; extra == 'hf'
Requires-Dist: transformers ; extra == 'hf'
Requires-Dist: ftfy ; extra == 'hf'
Requires-Dist: accelerate ; extra == 'hf'
